LICENSE.txt
MANIFEST.in
README.md
setup.py
xulpymoney.desktop
xulpymoney.pro
doc/Doxyfile
doc/ENTITY_RELATIONSHIP.md
doc/index.dox
xulpymoney/__init__.py
xulpymoney/admin_pg.py
xulpymoney/call_by_name.py
xulpymoney/casts.py
xulpymoney/connection_pg.py
xulpymoney/connection_pg_qt.py
xulpymoney/database_update.py
xulpymoney/datetime_functions.py
xulpymoney/decorators.py
xulpymoney/github.py
xulpymoney/hardcoded_strings.py
xulpymoney/internet.py
xulpymoney/investing_com.py
xulpymoney/iocalculations.py
xulpymoney/libcounter.py
xulpymoney/libmanagers.py
xulpymoney/libxulpymoneyfunctions.py
xulpymoney/libxulpymoneytypes.py
xulpymoney/mem.py
xulpymoney/package_resources.py
xulpymoney/shortcuts.py
xulpymoney/translationlanguages.py
xulpymoney/version.py
xulpymoney/xulpymoney.py
xulpymoney/xulpymoney_simulation_indexrange.py
xulpymoney.egg-info/PKG-INFO
xulpymoney.egg-info/SOURCES.txt
xulpymoney.egg-info/dependency_links.txt
xulpymoney.egg-info/entry_points.txt
xulpymoney.egg-info/not-zip-safe
xulpymoney.egg-info/requires.txt
xulpymoney.egg-info/top_level.txt
xulpymoney/external/__init__.py
xulpymoney/external/change_by_x.py
xulpymoney/external/geckodriver
xulpymoney/external/investment_com_downloads.py
xulpymoney/external/plus_minus.py
xulpymoney/external/trending_half.py
xulpymoney/i18n/xulpymoney_en.qm
xulpymoney/i18n/xulpymoney_en.ts
xulpymoney/i18n/xulpymoney_es.qm
xulpymoney/i18n/xulpymoney_es.ts
xulpymoney/i18n/xulpymoney_fr.qm
xulpymoney/i18n/xulpymoney_fr.ts
xulpymoney/i18n/xulpymoney_ro.qm
xulpymoney/i18n/xulpymoney_ro.ts
xulpymoney/i18n/xulpymoney_ru.qm
xulpymoney/i18n/xulpymoney_ru.ts
xulpymoney/images/14_layer_visible.png
xulpymoney/images/Money.png
xulpymoney/images/__init__.py
xulpymoney/images/add.png
xulpymoney/images/admin.png
xulpymoney/images/alarm_clock.png
xulpymoney/images/bank.png
xulpymoney/images/belgium.gif
xulpymoney/images/benchmark.png
xulpymoney/images/books.png
xulpymoney/images/bundle.png
xulpymoney/images/button_cancel.png
xulpymoney/images/button_ok.png
xulpymoney/images/cakes.png
xulpymoney/images/checkbox0.png
xulpymoney/images/checkbox1.png
xulpymoney/images/china.gif
xulpymoney/images/clipboard_copy.png
xulpymoney/images/cloud_download.png
